{
  "os_list": [
        {
            "description": "LibreELEC is a fast and user-friendly Kodi Entertainment Center distribution.",
            "group": "Media",
            "icon": "http://releases.libreelec.tv/noobs/LibreELEC_RPi/LibreELEC_RPi.png",
            "marketing_info": "http://releases.libreelec.tv/noobs/LibreELEC_RPi/marketing.tar",
            "nominal_size": 1024,
            "os_info": "http://releases.libreelec.tv/noobs/LibreELEC_RPi/os.json",
            "os_name": "LibreELEC_RPi",
            "partition_setup": "http://releases.libreelec.tv/noobs/LibreELEC_RPi/partition_setup.sh",
            "partitions_info": "http://releases.libreelec.tv/noobs/LibreELEC_RPi/partitions.json",
            "release_date": "2020-10-24",
            "supported_hex_revisions": "2,3,4,5,6,7,8,9,d,e,f,10,11,12,14,19,0092",
            "supported_models": [
                "Pi Model",
                "Pi Compute Module Rev",
                "Pi Zero"
            ],
            "supports_backup": true,
            "tarballs": [
                "http://releases.libreelec.tv/noobs/LibreELEC_RPi/System.tar.xz",
                "http://releases.libreelec.tv/noobs/LibreELEC_RPi/Storage.tar.xz"
            ],
            "url": "https://libreelec.tv/",
            "version": "9.2.6"
        }
,
        {
            "description": "LibreELEC is a fast and user-friendly Kodi Entertainment Center distribution.",
            "group": "Media",
            "icon": "http://releases.libreelec.tv/noobs/LibreELEC_RPi2/LibreELEC_RPi2.png",
            "marketing_info": "http://releases.libreelec.tv/noobs/LibreELEC_RPi2/marketing.tar",
            "nominal_size": 1024,
            "os_info": "http://releases.libreelec.tv/noobs/LibreELEC_RPi2/os.json",
            "os_name": "LibreELEC_RPi2",
            "partition_setup": "http://releases.libreelec.tv/noobs/LibreELEC_RPi2/partition_setup.sh",
            "partitions_info": "http://releases.libreelec.tv/noobs/LibreELEC_RPi2/partitions.json",
            "release_date": "2024-01-11",
            "supported_hex_revisions": "1040,1041,2082",
            "supported_models": [
                "Pi 2",
                "Pi 3 Model B",
                "Pi Compute Module 3"
            ],
            "supports_backup": true,
            "tarballs": [
                "http://releases.libreelec.tv/noobs/LibreELEC_RPi2/System.tar.xz",
                "http://releases.libreelec.tv/noobs/LibreELEC_RPi2/Storage.tar.xz"
            ],
            "url": "https://libreelec.tv/",
            "version": "11.0.5"
        }
,
        {
            "description": "LibreELEC is a fast and user-friendly Kodi Entertainment Center distribution.",
            "group": "Media",
            "icon": "http://releases.libreelec.tv/noobs/LibreELEC_RPi4/LibreELEC_RPi4.png",
            "marketing_info": "http://releases.libreelec.tv/noobs/LibreELEC_RPi4/marketing.tar",
            "nominal_size": 1024,
            "os_info": "http://releases.libreelec.tv/noobs/LibreELEC_RPi4/os.json",
            "os_name": "LibreELEC_RPi4",
            "partition_setup": "http://releases.libreelec.tv/noobs/LibreELEC_RPi4/partition_setup.sh",
            "partitions_info": "http://releases.libreelec.tv/noobs/LibreELEC_RPi4/partitions.json",
            "release_date": "2024-01-11",
            "supported_hex_revisions": "",
            "supported_models": [
                "Pi 4"
            ],
            "supports_backup": true,
            "tarballs": [
                "http://releases.libreelec.tv/noobs/LibreELEC_RPi4/System.tar.xz",
                "http://releases.libreelec.tv/noobs/LibreELEC_RPi4/Storage.tar.xz"
            ],
            "url": "https://libreelec.tv/",
            "version": "11.0.5"
        }
,
        {
            "description": "LibreELEC is a fast and user-friendly Kodi Entertainment Center distribution.",
            "group": "Media",
            "icon": "http://releases.libreelec.tv/noobs/LibreELEC_RPi5/LibreELEC_RPi5.png",
            "marketing_info": "http://releases.libreelec.tv/noobs/LibreELEC_RPi5/marketing.tar",
            "nominal_size": 1024,
            "os_info": "http://releases.libreelec.tv/noobs/LibreELEC_RPi5/os.json",
            "os_name": "LibreELEC_RPi5",
            "partition_setup": "http://releases.libreelec.tv/noobs/LibreELEC_RPi5/partition_setup.sh",
            "partitions_info": "http://releases.libreelec.tv/noobs/LibreELEC_RPi5/partitions.json",
            "release_date": "2024-01-11",
            "supported_hex_revisions": "",
            "supported_models": [
                "Pi 5"
            ],
            "supports_backup": true,
            "tarballs": [
                "http://releases.libreelec.tv/noobs/LibreELEC_RPi5/System.tar.xz",
                "http://releases.libreelec.tv/noobs/LibreELEC_RPi5/Storage.tar.xz"
            ],
            "url": "https://libreelec.tv/",
            "version": "11.0.5"
        }
,
        {
            "os_name": "LibreELEC_RPi2_926",
            "description": "LibreELEC is a fast and user-friendly Kodi Entertainment Center distribution.",
            "release_date": "2020-10-25",
            "supported_models": [
                "Pi 2",
                "Pi 3"
            ],
            "supports_usb_boot":       true,
            "supports_usb_root":       true,
            "version": "9.2.6",
            "supports_backup": true,
            "group": "Media",
            "nominal_size": 1024,
            "os_info":         "http://downloads.sourceforge.net/project/pinn/os/LibreELEC_RPi2_926/os.json",
            "partitions_info": "http://downloads.sourceforge.net/project/pinn/os/LibreELEC_RPi2_926/partitions.json",
            "icon":            "http://downloads.sourceforge.net/project/pinn/os/LibreELEC_RPi2_926/LibreELEC_RPi2_926.png",
            "marketing_info":  "http://downloads.sourceforge.net/project/pinn/os/LibreELEC_RPi2_926/marketing.tar",
            "partition_setup": "http://downloads.sourceforge.net/project/pinn/os/LibreELEC_RPi2_926/partition_setup.sh",
            "tarballs": [
                               "http://downloads.sourceforge.net/project/pinn/os/LibreELEC_RPi2_926/System.tar.xz",
                               "http://downloads.sourceforge.net/project/pinn/os/LibreELEC_RPi2_926/Storage.tar.xz"
            ],
            "url": "https://libreelec.tv/2020/11/02/libreelec-leia-9-2-6/"
        }
  ]
}
